{
  "Conjunto": [ "0", "1" ],
  "Estados": [
    {
      "Nome": "q1"
    },
    {
      "Nome": "q2"
    }
  ],
  "FuncaoPrograma": [
    {
      "Origem": {
        "Nome": "q1"
      },
      "Destino": {
        "Nome": "q1"
      },
      "Simbolo": "0"
    },
    {
      "Origem": {
        "Nome": "q1"
      },
      "Destino": {
        "Nome": "q2"
      },
      "Simbolo": "1"
    },
    {
      "Origem": {
        "Nome": "q2"
      },
      "Destino": {
        "Nome": "q1"
      },
      "Simbolo": "0"
    },
    {
      "Origem": {
        "Nome": "q2"
      },
      "Destino": {
        "Nome": "q2"
      },
      "Simbolo": "1"
    }
  ],
  "EstadoInicial": {
    "Nome": "q1"
  },
  "EstadosFinais": [
    {
      "Nome": "q1"
    }
  ]
}